<annotation>
	<folder>images</folder>
	<filename>PennPed00069.png</filename>
	<path>/home/ml/images/PennPed00069.png</path>
	<source>
		<database>Unknown</database>
	</source>
	<size>
		<width>388</width>
		<height>345</height>
		<depth>3</depth>
	</size>
	<segmented>0</segmented>
	<object>
		<name>person</name>
		<pose>Unspecified</pose>
		<truncated>0</truncated>
		<difficult>0</difficult>
		<bndbox>
			<xmin>49</xmin>
			<ymin>31</ymin>
			<xmax>152</xmax>
			<ymax>335</ymax>
		</bndbox>
	</object>
	<object>
		<name>person</name>
		<pose>Unspecified</pose>
		<truncated>0</truncated>
		<difficult>0</difficult>
		<bndbox>
			<xmin>170</xmin>
			<ymin>33</ymin>
			<xmax>277</xmax>
			<ymax>312</ymax>
		</bndbox>
	</object>
</annotation>
