<annotation>
	<folder>images</folder>
	<filename>PennPed00091.png</filename>
	<path>/home/ml/images/PennPed00091.png</path>
	<source>
		<database>Unknown</database>
	</source>
	<size>
		<width>372</width>
		<height>324</height>
		<depth>3</depth>
	</size>
	<segmented>0</segmented>
	<object>
		<name>person</name>
		<pose>Unspecified</pose>
		<truncated>0</truncated>
		<difficult>0</difficult>
		<bndbox>
			<xmin>235</xmin>
			<ymin>18</ymin>
			<xmax>335</xmax>
			<ymax>321</ymax>
		</bndbox>
	</object>
</annotation>
